act_scio-0.0.62-py3.12-nspkg.pth
act/scio/__init__.py
act/scio/alias.py
act/scio/aliasregex.py
act/scio/analyze.py
act/scio/api.py
act/scio/config.py
act/scio/es.py
act/scio/logsetup.py
act/scio/models.py
act/scio/nltk_download.py
act/scio/plugin.py
act/scio/scio_config.py
act/scio/submit.py
act/scio/tika_engine.py
act/scio/tlp.py
act/scio/upload.py
act/scio/vocabulary.py
act/scio/etc/feeds.txt
act/scio/etc/scio.ini
act/scio/etc/secstoplist.txt
act/scio/etc/plugins/country_aliases.cfg
act/scio/etc/plugins/locations.ini
act/scio/etc/plugins/openai.ini
act/scio/etc/plugins/sectors.cfg
act/scio/etc/plugins/sectors.ini
act/scio/etc/plugins/ta_aliases.cfg
act/scio/etc/plugins/threatactor_pattern.ini
act/scio/etc/plugins/tools.cfg
act/scio/etc/plugins/tools_pattern.ini
act/scio/feeds/__init__.py
act/scio/feeds/analyze.py
act/scio/feeds/cache.py
act/scio/feeds/conf.py
act/scio/feeds/download.py
act/scio/feeds/extract.py
act/scio/feeds/feeds.py
act/scio/feeds/upload.py
act/scio/plugins/__init__.py
act/scio/plugins/indicators.py
act/scio/plugins/locations.py
act/scio/plugins/mitre_attack.py
act/scio/plugins/openai.py
act/scio/plugins/pos_tag.py
act/scio/plugins/sectors.py
act/scio/plugins/threatactor_nlp.py
act/scio/plugins/threatactor_pattern.py
act/scio/plugins/tools_pattern.py
act/scio/plugins/vulnerabilities.py
act/scio/vendor/ISO-3166-countries-with-regional-codes.json
act/scio/vendor/cities15000.txt
act/scio/vendor/countryInfo.txt
act_scio-0.0.62.dist-info/LICENSE
act_scio-0.0.62.dist-info/METADATA
act_scio-0.0.62.dist-info/WHEEL
act_scio-0.0.62.dist-info/entry_points.txt
act_scio-0.0.62.dist-info/namespace_packages.txt
act_scio-0.0.62.dist-info/top_level.txt
act_scio-0.0.62.dist-info/zip-safe
act_scio-0.0.62.dist-info/RECORD
