Metadata-Version: 2.1
Name: act-scio
Version: 0.0.62
Summary: ACT SCIO
Home-page: https://github.com/mnemonic-no/act-scio2
Author: mnemonic AS
Author-email: opensource@mnemonic.no
License: ISC
Keywords: ACT,mnemonic
Classifier: Development Status :: 4 - Beta
Classifier: Topic :: Utilities
Classifier: License :: OSI Approved :: ISC License (ISCL)
Requires-Python: >=3.6, <4
License-File: LICENSE
Requires-Dist: addict
Requires-Dist: aiofiles
Requires-Dist: beautifulsoup4
Requires-Dist: bs4
Requires-Dist: caep
Requires-Dist: elasticsearch >=8.0.0
Requires-Dist: fastapi
Requires-Dist: feedparser
Requires-Dist: greenstalk >=2.0.0
Requires-Dist: ipaddress
Requires-Dist: justext
Requires-Dist: nltk
Requires-Dist: openai
Requires-Dist: pydantic <2.0.0,>=1.9.0
Requires-Dist: pytest-asyncio
Requires-Dist: pytest
Requires-Dist: python-magic
Requires-Dist: pytz
Requires-Dist: requests
Requires-Dist: tika
Requires-Dist: urllib3
Requires-Dist: uvicorn
